rename.py
rename-22.12.0.dist-info/METADATA
rename-22.12.0.dist-info/WHEEL
rename-22.12.0.dist-info/entry_points.txt
rename-22.12.0.dist-info/licenses/LICENSE.txt
rename-22.12.0.dist-info/RECORD
