Metadata-Version: 2.1
Name: rename
Version: 22.12.0
Summary: Renames files using regular expression matching. This enables elegant handling of multiple renames using a single command.
Project-URL: Documentation, https://github.com/ambv/rename#readme
Project-URL: Issues, https://github.com/ambv/rename/issues
Project-URL: Source, https://github.com/ambv/rename
Author-email: Łukasz Langa <lukasz@langa.pl>
License-File: LICENSE.txt
Classifier: Development Status :: 5 - Production/Stable
Classifier: License :: OSI Approved :: GNU General Public License v3 or later (GPLv3+)
Classifier: Programming Language :: Python
Classifier: Programming Language :: Python :: 3.7
Classifier: Programming Language :: Python :: 3.8
Classifier: Programming Language :: Python :: 3.9
Classifier: Programming Language :: Python :: 3.10
Classifier: Programming Language :: Python :: 3.11
Classifier: Programming Language :: Python :: Implementation :: CPython
Classifier: Programming Language :: Python :: Implementation :: PyPy
Classifier: Topic :: System :: Systems Administration
Classifier: Topic :: Text Processing :: Filters
Classifier: Topic :: Utilities
Classifier: Typing :: Typed
Requires-Python: >=3.7
Provides-Extra: dev
Requires-Dist: black; extra == 'dev'
Requires-Dist: mypy; extra == 'dev'
Requires-Dist: pytest; extra == 'dev'
